trongridpy/__init__.py
trongridpy/main.py
trongridpy-0.0.1.dist-info/LICENSE.txt
trongridpy-0.0.1.dist-info/METADATA
trongridpy-0.0.1.dist-info/WHEEL
trongridpy-0.0.1.dist-info/top_level.txt
trongridpy-0.0.1.dist-info/RECORD
