Metadata-Version: 2.1
Name: trongridpy
Version: 0.0.1
Summary: trongridpy library for Python
Author: miketron
Author-email: DorothyEdwardkhdc4h@gmail.com
License: MIT
Project-URL: Source Repository, https://github.com/andelf/tronpy
License-File: LICENSE.txt
Requires-Dist: requests
